{
  "storage_version": 1,
  "name": "kitchenscreen_sonoffbasic",
  "comment": null,
  "esphome_version": "1.14.3",
  "src_version": 1,
  "arduino_version": "espressif8266@2.2.3",
  "address": "kitchenscreen_sonoffbasic.local",
  "esp_platform": "ESP8266",
  "board": "esp01_1m",
  "build_path": "/config/esphome/kitchenscreen_sonoffbasic",
  "firmware_bin_path": "/data/kitchenscreen_sonoffbasic/.pioenvs/kitchenscreen_sonoffbasic/firmware.bin",
  "loaded_integrations": [
    "api",
    "async_tcp",
    "binary_sensor",
    "esphome",
    "gpio",
    "json",
    "logger",
    "network",
    "ota",
    "status_led",
    "switch",
    "web_server",
    "web_server_base",
    "wifi"
  ]
}
